{
  "get": [
    {
      "COIL_NO":"03S89274A",
      "STORAGE_LOCA":"CPL1000"
    },
    {
      "COIL_NO":"11K39880",
      "STORAGE_LOCA":"CPL1000"
    },
    {
      "COIL_NO":"03S37428B",
      "STORAGE_LOCA":"CPL1000"
    },
    {
      "COIL_NO":"06S44946",
      "STORAGE_LOCA":"CPL1000"
    },
    {
      "COIL_NO":"06S44326",
      "STORAGE_LOCA":"CPL1000"
    },
    {
      "COIL_NO":"06S44328",
      "STORAGE_LOCA":"CPL1000"
    },
    {
      "COIL_NO":"06S44331",
      "STORAGE_LOCA":"CPL1000"
    },
    {
      "COIL_NO":"06S45001",
      "STORAGE_LOCA":"CPL4000"
    },
    {
      "COIL_NO":"06S44043",
      "STORAGE_LOCA":"CPL4000"
    },
    {
      "COIL_NO":"06S70947",
      "STORAGE_LOCA":"CPL4000"
    },
    {
      "COIL_NO":"06S43440",
      "STORAGE_LOCA":"CPL4000"
    },
    {
      "COIL_NO":"06S70840",
      "STORAGE_LOCA":"CPL4000"
    },
    {
      "COIL_NO":"06S70999",
      "STORAGE_LOCA":"CPL4000"
    },
    {
      "COIL_NO":"06S44610",
      "STORAGE_LOCA":"CPL4000"
    },
    {
      "COIL_NO":"06S45855",
      "STORAGE_LOCA":"CPL4000"
    }
  ]
}